<annotation>
	<folder>JPEGImages</folder>
	<filename>1739.jpg</filename>
	<path>C:\Users\Lenovo\Desktop\VOC2007_v2\JPEGImages\1739.jpg</path>
	<source>
		<database>Unknown</database>
	</source>
	<size>
		<width>354</width>
		<height>72</height>
		<depth>3</depth>
	</size>
	<segmented>0</segmented>
	<object>
		<name>Exposed reinforcement</name>
		<pose>Unspecified</pose>
		<truncated>1</truncated>
		<difficult>0</difficult>
		<bndbox>
			<xmin>1</xmin>
			<ymin>45</ymin>
			<xmax>56</xmax>
			<ymax>51</ymax>
		</bndbox>
	</object>
	<object>
		<name>Exposed reinforcement</name>
		<pose>Unspecified</pose>
		<truncated>0</truncated>
		<difficult>0</difficult>
		<bndbox>
			<xmin>82</xmin>
			<ymin>43</ymin>
			<xmax>132</xmax>
			<ymax>54</ymax>
		</bndbox>
	</object>
	<object>
		<name>Exposed reinforcement</name>
		<pose>Unspecified</pose>
		<truncated>0</truncated>
		<difficult>0</difficult>
		<bndbox>
			<xmin>155</xmin>
			<ymin>45</ymin>
			<xmax>340</xmax>
			<ymax>53</ymax>
		</bndbox>
	</object>
</annotation>
