<annotation>
	<folder>JPEGImages</folder>
	<filename>3208.jpg</filename>
	<path>C:\Users\Lenovo\Desktop\VOC2007_v2\JPEGImages\3208.jpg</path>
	<source>
		<database>Unknown</database>
	</source>
	<size>
		<width>129</width>
		<height>144</height>
		<depth>3</depth>
	</size>
	<segmented>0</segmented>
	<object>
		<name>Corrosion</name>
		<pose>Unspecified</pose>
		<truncated>0</truncated>
		<difficult>0</difficult>
		<bndbox>
			<xmin>52</xmin>
			<ymin>47</ymin>
			<xmax>83</xmax>
			<ymax>77</ymax>
		</bndbox>
	</object>
</annotation>
